FancyTranslator/__init__.py
FancyTranslator/classes.py
FancyTranslator/methods.py
pyfancytranslator-1.1.1.dist-info/METADATA
pyfancytranslator-1.1.1.dist-info/WHEEL
pyfancytranslator-1.1.1.dist-info/top_level.txt
pyfancytranslator-1.1.1.dist-info/RECORD
