Metadata-Version: 2.1
Name: pyfancytranslator
Version: 1.1.1
Summary: A well built translator with placeholders
Author-email: Ashenguard <ashenguard@agmstudio.xyz>
Project-URL: Homepage, https://github.com/agm-studio/fancytranslator
Project-URL: Bug Tracker, https://github.com/agm-studio/fancytranslator/issues
Classifier: Programming Language :: Python :: 3
Classifier: License :: OSI Approved :: MIT License
Classifier: Development Status :: 5 - Production/Stable
Classifier: Operating System :: OS Independent
Requires-Python: >=3.12
